{"assets/images/img1-1.png":["assets/images/img1-1.png"],"assets/images/img1.png":["assets/images/img1.png"],"assets/images/img2.png":["assets/images/img2.png"],"assets/images/img3.png":["assets/images/img3.png"],"assets/images/img4.png":["assets/images/img4.png"],"assets/images/img5.png":["assets/images/img5.png"],"assets/images/img6.png":["assets/images/img6.png"],"assets/images/img7.png":["assets/images/img7.png"],"assets/images/img8.png":["assets/images/img8.png"],"assets/images/img9.png":["assets/images/img9.png"],"packages/cupertino_icons/assets/CupertinoIcons.ttf":["packages/cupertino_icons/assets/CupertinoIcons.ttf"]}